oneNeuron/__init__.py
oneNeuron/perceptron.py
oneNeuron_pypi_tirth1-0.0.1.dist-info/LICENSE
oneNeuron_pypi_tirth1-0.0.1.dist-info/METADATA
oneNeuron_pypi_tirth1-0.0.1.dist-info/WHEEL
oneNeuron_pypi_tirth1-0.0.1.dist-info/top_level.txt
oneNeuron_pypi_tirth1-0.0.1.dist-info/RECORD
